CMakeLists.txt
LICENSE
MANIFEST.in
README.md
_debug_hints.txt
a.py
installed.my.txt
installed_modules.avito.txt
pyproject.toml
setup.py
pylem/CMakeLists.txt
pylem/__init__.py
pylem/pylem_binary.py
pylem.egg-info/PKG-INFO
pylem.egg-info/SOURCES.txt
pylem.egg-info/dependency_links.txt
pylem.egg-info/not-zip-safe
pylem.egg-info/requires.txt
pylem.egg-info/top_level.txt
pylem/Dicts/__init__.py
pylem/binding/main.cpp
pylem/morph_dict/CMakeLists.txt
pylem/morph_dict.s/CMakeLists.txt
pylem/morph_dict.s/AgramtabLib/AncodePattern.cpp
pylem/morph_dict.s/AgramtabLib/AncodePattern.h
pylem/morph_dict.s/AgramtabLib/CMakeLists.txt
pylem/morph_dict.s/AgramtabLib/EngGramTab.cpp
pylem/morph_dict.s/AgramtabLib/EngGramTab.h
pylem/morph_dict.s/AgramtabLib/GerGramTab.cpp
pylem/morph_dict.s/AgramtabLib/GerGramTab.h
pylem/morph_dict.s/AgramtabLib/GramInfo.h
pylem/morph_dict.s/AgramtabLib/RusGramTab.cpp
pylem/morph_dict.s/AgramtabLib/RusGramTab.h
pylem/morph_dict.s/AgramtabLib/agramtab_.cpp
pylem/morph_dict.s/AgramtabLib/agramtab_.h
pylem/morph_dict.s/AgramtabLib/eng_consts.h
pylem/morph_dict.s/AgramtabLib/ger_consts.h
pylem/morph_dict.s/AgramtabLib/rus_consts.h
pylem/morph_dict.s/AgramtabLib/tests/CheckGramTab/CMakeLists.txt
pylem/morph_dict.s/AgramtabLib/tests/CheckGramTab/CheckGramTab.cpp
pylem/morph_dict.s/LemmatizerBaseLib/CMakeLists.txt
pylem/morph_dict.s/LemmatizerBaseLib/CreatePredictionBase.cpp
pylem/morph_dict.s/LemmatizerBaseLib/LemmaInfoSerialize.h
pylem/morph_dict.s/LemmatizerBaseLib/Lemmatizers.cpp
pylem/morph_dict.s/LemmatizerBaseLib/Lemmatizers.h
pylem/morph_dict.s/LemmatizerBaseLib/MorphAutomBuilder.cpp
pylem/morph_dict.s/LemmatizerBaseLib/MorphAutomBuilder.h
pylem/morph_dict.s/LemmatizerBaseLib/MorphAutomat.cpp
pylem/morph_dict.s/LemmatizerBaseLib/MorphAutomat.h
pylem/morph_dict.s/LemmatizerBaseLib/MorphDict.cpp
pylem/morph_dict.s/LemmatizerBaseLib/MorphDict.h
pylem/morph_dict.s/LemmatizerBaseLib/MorphDictBuilder.cpp
pylem/morph_dict.s/LemmatizerBaseLib/MorphDictBuilder.h
pylem/morph_dict.s/LemmatizerBaseLib/MorphanHolder.cpp
pylem/morph_dict.s/LemmatizerBaseLib/MorphanHolder.h
pylem/morph_dict.s/LemmatizerBaseLib/Paradigm.cpp
