Metadata-Version: 2.1
Name: pylem
Version: 0.0.18
Summary: Morphological analysis, dictionary lemmatization for Russian, German and English
Home-page: http://www.aot.ru
Author: Alexey Sokirko
Author-email: sokirko@yandex.ru
License: MIT
Platform: UNKNOWN
Requires-Python: >=3.6
Provides-Extra: test
License-File: LICENSE
